childespy/__init__.py
childespy/childespy.py
childespy-1.0.1.dist-info/LICENSE
childespy-1.0.1.dist-info/METADATA
childespy-1.0.1.dist-info/WHEEL
childespy-1.0.1.dist-info/top_level.txt
childespy-1.0.1.dist-info/RECORD
