Metadata-Version: 2.1
Name: childespy
Version: 1.0.1
Summary: UNKNOWN
Home-page: https://github.com/langcog/childespy
Author: Jessica Mankewitz
Author-email: jmank@stanford.edu
License: UNKNOWN
Platform: UNKNOWN
Classifier: Programming Language :: Python :: 3
Classifier: License :: OSI Approved :: GNU Affero General Public License v3
Classifier: Operating System :: OS Independent
Requires-Python: >=3.6
Requires-Dist: rpy2 (>=3.3.5)
Requires-Dist: numpy (>=1.19.2)
Requires-Dist: pandas (>=1.1.2)
